MANIFEST.in
README.rst
setup.py
docs/HISTORY.txt
docs/INSTALL.txt
docs/LICENSE.GPL
docs/LICENSE.txt
seantis/__init__.py
seantis.dir.facility.egg-info/PKG-INFO
seantis.dir.facility.egg-info/SOURCES.txt
seantis.dir.facility.egg-info/dependency_links.txt
seantis.dir.facility.egg-info/entry_points.txt
seantis.dir.facility.egg-info/namespace_packages.txt
seantis.dir.facility.egg-info/not-zip-safe
seantis.dir.facility.egg-info/requires.txt
seantis.dir.facility.egg-info/top_level.txt
seantis/dir/__init__.py
seantis/dir/facility/__init__.py
seantis/dir/facility/configure.zcml
seantis/dir/facility/directory.py
seantis/dir/facility/item.py
seantis/dir/facility/setuphandlers.py
seantis/dir/facility/sync.sh
seantis/dir/facility/upgrades.py
seantis/dir/facility/utils.py
seantis/dir/facility/version.txt
seantis/dir/facility/css/izug/directory.css
seantis/dir/facility/css/izug/item.css
seantis/dir/facility/css/sunburst/directory.css
seantis/dir/facility/css/sunburst/item.css
seantis/dir/facility/css/teamraum/directory.css
seantis/dir/facility/css/teamraum/item.css
seantis/dir/facility/locales/seantis.dir.facility.pot
seantis/dir/facility/locales/de/LC_MESSAGES/plone.po
seantis/dir/facility/locales/de/LC_MESSAGES/seantis.dir.facility.po
seantis/dir/facility/profiles/default/import_steps.xml
seantis/dir/facility/profiles/default/jsregistry.xml
seantis/dir/facility/profiles/default/metadata.xml
seantis/dir/facility/profiles/default/types.xml
seantis/dir/facility/profiles/default/types/seantis.dir.facility.directory.xml
seantis/dir/facility/profiles/default/types/seantis.dir.facility.item.xml
seantis/dir/facility/profiles/izug_basetheme/cssregistry.xml
seantis/dir/facility/profiles/izug_basetheme/metadata.xml
seantis/dir/facility/profiles/izug_basetheme/viewlets.xml
seantis/dir/facility/profiles/sunburst/cssregistry.xml
seantis/dir/facility/profiles/sunburst/metadata.xml
seantis/dir/facility/profiles/teamraum/cssregistry.xml
seantis/dir/facility/profiles/teamraum/metadata.xml
seantis/dir/facility/scss/facility.scss
seantis/dir/facility/templates/directory.pt
seantis/dir/facility/templates/directorydetail.pt
seantis/dir/facility/templates/item.pt
seantis/dir/facility/templates/itemdetail.pt
seantis/dir/facility/templates/map.pt
seantis/dir/facility/tests/__init__.py
seantis/dir/facility/tests/layer.py
