Metadata-Version: 1.1
Name: seantis.dir.facility
Version: 1.8
Summary: Facility Directory for Seantis Reservation
Home-page: http://svn.plone.org/svn/collective/
Author: Seantis GmbH
Author-email: info@seantis.ch
License: GPL
Platform: UNKNOWN
Classifier: Framework :: Plone
Classifier: Framework :: Plone :: 4.3
Classifier: Programming Language :: Python
